Workbook

Sheet Data Considered
A1: Parameter | B1: Value
A2: Number of weeks | B2: 1 to 104
A3: Lead Time | B3: 2
A4: OUL Factor | B4: 3
A5: Initial Inventory | B5: 80
A6: Demand Distribution | B6: NORM.INV(RAND(),20,5)
A7: Retailer Selling Price | B7: 180 | C7: Retailer overhead | D7: 10
A8: Retailer Purchase Price | B8: 140 | C8: Retailer profit | D8: 30
A9: Distributor Selling Price | B9: 140 | C9: Distributor overhead | D9: 7
A10: Distributor Purchase Price | B10: 100 | C10: Distributor profit | D10: 33
A11: Manufacturer Selling Price | B11: 100 | C11: Manufacturer overhead | D11: 5
A12: Manufacturer Production Cost | B12: 50 | C12: Manufacturer profit | D12: 45
A13: Credit [Customer to Retailer] | B13: 0
A14: Credit [Retailer to Distributor] | B14: 2
A15: Credit [Distributor to Manufacturer] | B15: 2
A16: Initial Cash [Retailer] | B16: 10000
A17: Initial Cash [Distributor] | B17: 30000
A18: Initial Cash [Manufacturer] | B18: 50000
A19: Holding cost per week per unit
A20: Retailer | B20: 15
A21: Distributor | B21: 10
A22: Manufacturer | B22: 5
A23: Shortage Cost per week per unit
A24: Retailer | B24: 40
A25: Distributor | B25: 30
A26: Manufacturer | B26: 40
A27: Performance Summary
A28: From Week | B28: 21
A29: To Week | B29: 80

Sheet Retailer
A1: WEEK | B1: CUSTOMER DEMAND | C1: FORECAST | D1: OUL | E1: GOODS RECEIVED | F1: BEGINNING INVENTORY | G1: INVENTORY POSITION | H1: ORDER PLACED TO DISTRIBUTOR | I1: GOODS AVAILABLE | J1: UNITS SOLD | K1: LOST SALES | L1: ENDING INVENTORY | M1: INVOICE TO CUSTOMER | N1: PAYMENT RECEIVED | O1: PURCHASE COST | P1: PAYMENT MADE TO DISTRIBUTOR | Q1: NET CASH FLOW | R1: CASH POSITION | S1: OVERHEAD EXPENSES | T1: HOLDING COST | U1: SHORTAGE COST | V1: INVENTORY WEEKS | W1: CASH TO CASH CYCLE TIME | X1: ACCOUNTS PAYABLE | Y1: ACCOUNTS RECEIVABLE
A2: 1 | B2: =Demand!B2 -> 25 | C2: =20 -> 20 | D2: =3*C2 -> 60 | E2: =0 -> 0 | F2: =IF(A2=1,'Data Considered'!$B$5,Retailer!L1+Retailer!E2) -> 80 | G2: =F2+IF(A2>1,H1,0) -> 80 | H2: =IF(D2>G2,D2-G2,0) -> 0 | I2: =F2 -> 80 | J2: =MIN(I2,B2) -> 25 | K2: =B2-J2 -> 0 | L2: =I2-J2 -> 55 | M2: =J2*'Data Considered'!$B$7 -> 4500 | N2: =IF(A2>'Data Considered'!$B$13,OFFSET(Retailer!M2,-'Data Considered'!$B$13,0),0) -> 4500 | O2: =E2*'Data Considered'!$B$8 -> 0 | P2: =IF(A2>'Data Considered'!$B$14,OFFSET(Retailer!O2,-'Data Considered'!$B$14,0),0) -> 0 | Q2: =N2-P2-T2-S2 -> 3425 | R2: =IF(A2=1,'Data Considered'!$B$16,Retailer!R1+Retailer!Q2) -> 10000 | S2: =J2*'Data Considered'!$D$7 -> 250 | T2: =L2*'Data Considered'!$B$20 -> 825 | U2: =K2*'Data Considered'!$B$24 -> 0 | V2: =ROUNDUP(L2/$B$108,0) -> 3 | W2: =V2+'Data Considered'!$B$13-'Data Considered'!$B$14 -> 1 | X2: =IF(A2>2,OFFSET(O2,-2,0),0)+S2 -> 250 | Y2: =M2 -> 4500
A3: =A2+1 -> 2 | B3: =Demand!B3 -> 24 | C3: =B2 -> 25 | D3: =3*C3 -> 75 | E3: =Distributor!J2 -> 0 | F3: =IF(A3=1,'Data Considered'!$B$5,Retailer!L2+Retailer!E3) -> 55 | G3: =F3+IF(A3>1,H2,0) -> 55 | H3: =IF(D3>G3,D3-G3,0) -> 20 | I3: =F3 -> 55 | J3: =MIN(I3,B3) -> 24 | K3: =B3-J3 -> 0 | L3: =I3-J3 -> 31 | M3: =J3*'Data Considered'!$B$7 -> 4320 | N3: =IF(A3>'Data Considered'!$B$13,OFFSET(Retailer!M3,-'Data Considered'!$B$13,0),0) -> 4320 | O3: =E3*'Data Considered'!$B$8 -> 0 | P3: =IF(A3>'Data Considered'!$B$14,OFFSET(Retailer!O3,-'Data Considered'!$B$14,0),0) -> 0 | Q3: =N3-P3-T3-S3 -> 3615 | R3: =IF(A3=1,'Data Considered'!$B$16,Retailer!R2+Retailer!Q3) -> 13615 | S3: =J3*'Data Considered'!$D$7 -> 240 | T3: =L3*'Data Considered'!$B$20 -> 465 | U3: =K3*'Data Considered'!$B$24 -> 0 | V3: =ROUNDUP(L3/$B$108,0) -> 2 | W3: =V3+'Data Considered'!$B$13-'Data Considered'!$B$14 -> 0 | X3: =IF(A3>2,OFFSET(O3,-2,0),0)+S3 -> 240 | Y3: =M3 -> 4320
A4: =A3+1 -> 3 | B4: =Demand!B4 -> 15 | C4: =ROUNDUP(AVERAGE(B2,B3),0) -> 25 | D4: =3*C4 -> 75 | E4: =Distributor!J3 -> 0 | F4: =IF(A4=1,'Data Considered'!$B$5,Retailer!L3+Retailer!E4) -> 31 | G4: =F4+IF(A4>1,H3,0) -> 51 | H4: =IF(D4>G4,D4-G4,0) -> 24 | I4: =F4 -> 31 | J4: =MIN(I4,B4) -> 15 | K4: =B4-J4 -> 0 | L4: =I4-J4 -> 16 | M4: =J4*'Data Considered'!$B$7 -> 2700 | N4: =IF(A4>'Data Considered'!$B$13,OFFSET(Retailer!M4,-'Data Considered'!$B$13,0),0) -> 2700 | O4: =E4*'Data Considered'!$B$8 -> 0 | P4: =IF(A4>'Data Considered'!$B$14,OFFSET(Retailer!O4,-'Data Considered'!$B$14,0),0) -> 0 | Q4: =N4-P4-T4-S4 -> 2310 | R4: =IF(A4=1,'Data Considered'!$B$16,Retailer!R3+Retailer!Q4) -> 15925 | S4: =J4*'Data Considered'!$D$7 -> 150 | T4: =L4*'Data Considered'!$B$20 -> 240 | U4: =K4*'Data Considered'!$B$24 -> 0 | V4: =ROUNDUP(L4/$B$108,0) -> 1 | W4: =V4+'Data Considered'!$B$13-'Data Considered'!$B$14 -> -1 | X4: =IF(A4>2,OFFSET(O4,-2,0),0)+S4 -> 150 | Y4: =M4 -> 2700
A5: =A4+1 -> 4 | B5: =Demand!B5 -> 21 | C5: =ROUNDUP(AVERAGE(B3,B4),0) -> 20 | D5: =3*C5 -> 60 | E5: =Distributor!J4 -> 20 | F5: =IF(A5=1,'Data Considered'!$B$5,Retailer!L4+Retailer!E5) -> 36 | G5: =F5+IF(A5>1,H4,0) -> 60 | H5: =IF(D5>G5,D5-G5,0) -> 0 | I5: =F5 -> 36 | J5: =MIN(I5,B5) -> 21 | K5: =B5-J5 -> 0 | L5: =I5-J5 -> 15 | M5: =J5*'Data Considered'!$B$7 -> 3780 | N5: =IF(A5>'Data Considered'!$B$13,OFFSET(Retailer!M5,-'Data Considered'!$B$13,0),0) -> 3780 | O5: =E5*'Data Considered'!$B$8 -> 2800 | P5: =IF(A5>'Data Considered'!$B$14,OFFSET(Retailer!O5,-'Data Considered'!$B$14,0),0) -> 0 | Q5: =N5-P5-T5-S5 -> 3345 | R5: =IF(A5=1,'Data Considered'!$B$16,Retailer!R4+Retailer!Q5) -> 19270 | S5: =J5*'Data Considered'!$D$7 -> 210 | T5: =L5*'Data Considered'!$B$20 -> 225 | U5: =K5*'Data Considered'!$B$24 -> 0 | V5: =ROUNDUP(L5/$B$108,0) -> 1 | W5: =V5+'Data Considered'!$B$13-'Data Considered'!$B$14 -> -1 | X5: =IF(A5>2,OFFSET(O5,-2,0),0)+S5 -> 210 | Y5: =M5 -> 3780
A6: =A5+1 -> 5 | B6: =Demand!B6 -> 26 | C6: =ROUNDUP(AVERAGE(B4,B5),0) -> 18 | D6: =3*C6 -> 54 | E6: =Distributor!J5 -> 24 | F6: =IF(A6=1,'Data Considered'!$B$5,Retailer!L5+Retailer!E6) -> 39 | G6: =F6+IF(A6>1,H5,0) -> 39 | H6: =IF(D6>G6,D6-G6,0) -> 15 | I6: =F6 -> 39 | J6: =MIN(I6,B6) -> 26 | K6: =B6-J6 -> 0 | L6: =I6-J6 -> 13 | M6: =J6*'Data Considered'!$B$7 -> 4680 | N6: =IF(A6>'Data Considered'!$B$13,OFFSET(Retailer!M6,-'Data Considered'!$B$13,0),0) -> 4680 | O6: =E6*'Data Considered'!$B$8 -> 3360 | P6: =IF(A6>'Data Considered'!$B$14,OFFSET(Retailer!O6,-'Data Considered'!$B$14,0),0) -> 0 | Q6: =N6-P6-T6-S6 -> 4225 | R6: =IF(A6=1,'Data Considered'!$B$16,Retailer!R5+Retailer!Q6) -> 23495 | S6: =J6*'Data Considered'!$D$7 -> 260 | T6: =L6*'Data Considered'!$B$20 -> 195 | U6: =K6*'Data Considered'!$B$24 -> 0 | V6: =ROUNDUP(L6/$B$108,0) -> 1 | W6: =V6+'Data Considered'!$B$13-'Data Considered'!$B$14 -> -1 | X6: =IF(A6>2,OFFSET(O6,-2,0),0)+S6 -> 260 | Y6: =M6 -> 4680
A7: =A6+1 -> 6 | B7: =Demand!B7 -> 24 | C7: =ROUNDUP(AVERAGE(B5,B6),0) -> 24 | D7: =3*C7 -> 72 | E7: =Distributor!J6 -> 0 | F7: =IF(A7=1,'Data Considered'!$B$5,Retailer!L6+Retailer!E7) -> 13 | G7: =F7+IF(A7>1,H6,0) -> 28 | H7: =IF(D7>G7,D7-G7,0) -> 44 | I7: =F7 -> 13 | J7: =MIN(I7,B7) -> 13 | K7: =B7-J7 -> 11 | L7: =I7-J7 -> 0 | M7: =J7*'Data Considered'!$B$7 -> 2340 | N7: =IF(A7>'Data Considered'!$B$13,OFFSET(Retailer!M7,-'Data Considered'!$B$13,0),0) -> 2340 | O7: =E7*'Data Considered'!$B$8 -> 0 | P7: =IF(A7>'Data Considered'!$B$14,OFFSET(Retailer!O7,-'Data Considered'!$B$14,0),0) -> 2800 | Q7: =N7-P7-T7-S7 -> -590 | R7: =IF(A7=1,'Data Considered'!$B$16,Retailer!R6+Retailer!Q7) -> 22905 | S7: =J7*'Data Considered'!$D$7 -> 130 | T7: =L7*'Data Considered'!$B$20 -> 0 | U7: =K7*'Data Considered'!$B$24 -> 440 | V7: =ROUNDUP(L7/$B$108,0) -> 0 | W7: =V7+'Data Considered'!$B$13-'Data Considered'!$B$14 -> -2 | X7: =IF(A7>2,OFFSET(O7,-2,0),0)+S7 -> 2930 | Y7: =M7 -> 2340
A8: =A7+1 -> 7 | B8: =Demand!B8 -> 26 | C8: =ROUNDUP(AVERAGE(B6,B7),0) -> 25 | D8: =3*C8 -> 75 | E8: =Distributor!J7 -> 15 | F8: =IF(A8=1,'Data Considered'!$B$5,Retailer!L7+Retailer!E8) -> 15 | G8: =F8+IF(A8>1,H7,0) -> 59 | H8: =IF(D8>G8,D8-G8,0) -> 16 | I8: =F8 -> 15 | J8: =MIN(I8,B8) -> 15 | K8: =B8-J8 -> 11 | L8: =I8-J8 -> 0 | M8: =J8*'Data Considered'!$B$7 -> 2700 | N8: =IF(A8>'Data Considered'!$B$13,OFFSET(Retailer!M8,-'Data Considered'!$B$13,0),0) -> 2700 | O8: =E8*'Data Considered'!$B$8 -> 2100 | P8: =IF(A8>'Data Considered'!$B$14,OFFSET(Retailer!O8,-'Data Considered'!$B$14,0),0) -> 3360 | Q8: =N8-P8-T8-S8 -> -810 | R8: =IF(A8=1,'Data Considered'!$B$16,Retailer!R7+Retailer!Q8) -> 22095 | S8: =J8*'Data Considered'!$D$7 -> 150 | T8: =L8*'Data Considered'!$B$20 -> 0 | U8: =K8*'Data Considered'!$B$24 -> 440 | V8: =ROUNDUP(L8/$B$108,0) -> 0 | W8: =V8+'Data Considered'!$B$13-'Data Considered'!$B$14 -> -2 | X8: =IF(A8>2,OFFSET(O8,-2,0),0)+S8 -> 3510 | Y8: =M8 -> 2700
A9: =A8+1 -> 8 | B9: =Demand!B9 -> 9 | C9: =ROUNDUP(AVERAGE(B7,B8),0) -> 25 | D9: =3*C9 -> 75 | E9: =Distributor!J8 -> 44 | F9: =IF(A9=1,'Data Considered'!$B$5,Retailer!L8+Retailer!E9) -> 44 | G9: =F9+IF(A9>1,H8,0) -> 60 | H9: =IF(D9>G9,D9-G9,0) -> 15 | I9: =F9 -> 44 | J9: =MIN(I9,B9) -> 9 | K9: =B9-J9 -> 0 | L9: =I9-J9 -> 35 | M9: =J9*'Data Considered'!$B$7 -> 1620 | N9: =IF(A9>'Data Considered'!$B$13,OFFSET(Retailer!M9,-'Data Considered'!$B$13,0),0) -> 1620 | O9: =E9*'Data Considered'!$B$8 -> 6160 | P9: =IF(A9>'Data Considered'!$B$14,OFFSET(Retailer!O9,-'Data Considered'!$B$14,0),0) -> 0 | Q9: =N9-P9-T9-S9 -> 1005 | R9: =IF(A9=1,'Data Considered'!$B$16,Retailer!R8+Retailer!Q9) -> 23100 | S9: =J9*'Data Considered'!$D$7 -> 90 | T9: =L9*'Data Considered'!$B$20 -> 525 | U9: =K9*'Data Considered'!$B$24 -> 0 | V9: =ROUNDUP(L9/$B$108,0) -> 2 | W9: =V9+'Data Considered'!$B$13-'Data Considered'!$B$14 -> 0 | X9: =IF(A9>2,OFFSET(O9,-2,0),0)+S9 -> 90 | Y9: =M9 -> 1620
A10: =A9+1 -> 9 | B10: =Demand!B10 -> 18 | C10: =ROUNDUP(AVERAGE(B8,B9),0) -> 18 | D10: =3*C10 -> 54 | E10: =Distributor!J9 -> 7 | F10: =IF(A10=1,'Data Considered'!$B$5,Retailer!L9+Retailer!E10) -> 42 | G10: =F10+IF(A10>1,H9,0) -> 57 | H10: =IF(D10>G10,D10-G10,0) -> 0 | I10: =F10 -> 42 | J10: =MIN(I10,B10) -> 18 | K10: =B10-J10 -> 0 | L10: =I10-J10 -> 24 | M10: =J10*'Data Considered'!$B$7 -> 3240 | N10: =IF(A10>'Data Considered'!$B$13,OFFSET(Retailer!M10,-'Data Considered'!$B$13,0),0) -> 3240 | O10: =E10*'Data Considered'!$B$8 -> 980 | P10: =IF(A10>'Data Considered'!$B$14,OFFSET(Retailer!O10,-'Data Considered'!$B$14,0),0) -> 2100 | Q10: =N10-P10-T10-S10 -> 600 | R10: =IF(A10=1,'Data Considered'!$B$16,Retailer!R9+Retailer!Q10) -> 23700 | S10: =J10*'Data Considered'!$D$7 -> 180 | T10: =L10*'Data Considered'!$B$20 -> 360 | U10: =K10*'Data Considered'!$B$24 -> 0 | V10: =ROUNDUP(L10/$B$108,0) -> 2 | W10: =V10+'Data Considered'!$B$13-'Data Considered'!$B$14 -> 0 | X10: =IF(A10>2,OFFSET(O10,-2,0),0)+S10 -> 2280 | Y10: =M10 -> 3240
A11: =A10+1 -> 10 | B11: =Demand!B11 -> 22 | C11: =ROUNDUP(AVERAGE(B9,B10),0) -> 14 | D11: =3*C11 -> 42 | E11: =Distributor!J10 -> 0 | F11: =IF(A11=1,'Data Considered'!$B$5,Retailer!L10+Retailer!E11) -> 24 | G11: =F11+IF(A11>1,H10,0) -> 24 | H11: =IF(D11>G11,D11-G11,0) -> 18 | I11: =F11 -> 24 | J11: =MIN(I11,B11) -> 22 | K11: =B11-J11 -> 0 | L11: =I11-J11 -> 2 | M11: =J11*'Data Considered'!$B$7 -> 3960 | N11: =IF(A11>'Data Considered'!$B$13,OFFSET(Retailer!M11,-'Data Considered'!$B$13,0),0) -> 3960 | O11: =E11*'Data Considered'!$B$8 -> 0 | P11: =IF(A11>'Data Considered'!$B$14,OFFSET(Retailer!O11,-'Data Considered'!$B$14,0),0) -> 6160 | Q11: =N11-P11-T11-S11 -> -2450 | R11: =IF(A11=1,'Data Considered'!$B$16,Retailer!R10+Retailer!Q11) -> 21250 | S11: =J11*'Data Considered'!$D$7 -> 220 | T11: =L11*'Data Considered'!$B$20 -> 30 | U11: =K11*'Data Considered'!$B$24 -> 0 | V11: =ROUNDUP(L11/$B$108,0) -> 1 | W11: =V11+'Data Considered'!$B$13-'Data Considered'!$B$14 -> -1 | X11: =IF(A11>2,OFFSET(O11,-2,0),0)+S11 -> 6380 | Y11: =M11 -> 3960
A12: =A11+1 -> 11 | B12: =Demand!B12 -> 23 | C12: =ROUNDUP(AVERAGE(B10,B11),0) -> 20 | D12: =3*C12 -> 60 | E12: =Distributor!J11 -> 0 | F12: =IF(A12=1,'Data Considered'!$B$5,Retailer!L11+Retailer!E12) -> 2 | G12: =F12+IF(A12>1,H11,0) -> 20 | H12: =IF(D12>G12,D12-G12,0) -> 40 | I12: =F12 -> 2 | J12: =MIN(I12,B12) -> 2 | K12: =B12-J12 -> 21 | L12: =I12-J12 -> 0 | M12: =J12*'Data Considered'!$B$7 -> 360 | N12: =IF(A12>'Data Considered'!$B$13,OFFSET(Retailer!M12,-'Data Considered'!$B$13,0),0) -> 360 | O12: =E12*'Data Considered'!$B$8 -> 0 | P12: =IF(A12>'Data Considered'!$B$14,OFFSET(Retailer!O12,-'Data Considered'!$B$14,0),0) -> 980 | Q12: =N12-P12-T12-S12 -> -640 | R12: =IF(A12=1,'Data Considered'!$B$16,Retailer!R11+Retailer!Q12) -> 20610 | S12: =J12*'Data Considered'!$D$7 -> 20 | T12: =L12*'Data Considered'!$B$20 -> 0 | U12: =K12*'Data Considered'!$B$24 -> 840 | V12: =ROUNDUP(L12/$B$108,0) -> 0 | W12: =V12+'Data Considered'!$B$13-'Data Considered'!$B$14 -> -2 | X12: =IF(A12>2,OFFSET(O12,-2,0),0)+S12 -> 1000 | Y12: =M12 -> 360
A13: =A12+1 -> 12 | B13: =Demand!B13 -> 24 | C13: =ROUNDUP(AVERAGE(B11,B12),0) -> 23 | D13: =3*C13 -> 69 | E13: =Distributor!J12 -> 18 | F13: =IF(A13=1,'Data Considered'!$B$5,Retailer!L12+Retailer!E13) -> 18 | G13: =F13+IF(A13>1,H12,0) -> 58 | H13: =IF(D13>G13,D13-G13,0) -> 11 | I13: =F13 -> 18 | J13: =MIN(I13,B13) -> 18 | K13: =B13-J13 -> 6 | L13: =I13-J13 -> 0 | M13: =J13*'Data Considered'!$B$7 -> 3240 | N13: =IF(A13>'Data Considered'!$B$13,OFFSET(Retailer!M13,-'Data Considered'!$B$13,0),0) -> 3240 | O13: =E13*'Data Considered'!$B$8 -> 2520 | P13: =IF(A13>'Data Considered'!$B$14,OFFSET(Retailer!O13,-'Data Considered'!$B$14,0),0) -> 0 | Q13: =N13-P13-T13-S13 -> 3060 | R13: =IF(A13=1,'Data Considered'!$B$16,Retailer!R12+Retailer!Q13) -> 23670 | S13: =J13*'Data Considered'!$D$7 -> 180 | T13: =L13*'Data Considered'!$B$20 -> 0 | U13: =K13*'Data Considered'!$B$24 -> 240 | V13: =ROUNDUP(L13/$B$108,0) -> 0 | W13: =V13+'Data Considered'!$B$13-'Data Considered'!$B$14 -> -2 | X13: =IF(A13>2,OFFSET(O13,-2,0),0)+S13 -> 180 | Y13: =M13 -> 3240
A14: =A13+1 -> 13 | B14: =Demand!B14 -> 20 | C14: =ROUNDUP(AVERAGE(B12,B13),0) -> 24 | D14: =3*C14 -> 72 | E14: =Distributor!J13 -> 32 | F14: =IF(A14=1,'Data Considered'!$B$5,Retailer!L13+Retailer!E14) -> 32 | G14: =F14+IF(A14>1,H13,0) -> 43 | H14: =IF(D14>G14,D14-G14,0) -> 29 | I14: =F14 -> 32 | J14: =MIN(I14,B14) -> 20 | K14: =B14-J14 -> 0 | L14: =I14-J14 -> 12 | M14: =J14*'Data Considered'!$B$7 -> 3600 | N14: =IF(A14>'Data Considered'!$B$13,OFFSET(Retailer!M14,-'Data Considered'!$B$13,0),0) -> 3600 | O14: =E14*'Data Considered'!$B$8 -> 4480 | P14: =IF(A14>'Data Considered'!$B$14,OFFSET(Retailer!O14,-'Data Considered'!$B$14,0),0) -> 0 | Q14: =N14-P14-T14-S14 -> 3220 | R14: =IF(A14=1,'Data Considered'!$B$16,Retailer!R13+Retailer!Q14) -> 26890 | S14: =J14*'Data Considered'!$D$7 -> 200 | T14: =L14*'Data Considered'!$B$20 -> 180 | U14: =K14*'Data Considered'!$B$24 -> 0 | V14: =ROUNDUP(L14/$B$108,0) -> 1 | W14: =V14+'Data Considered'!$B$13-'Data Considered'!$B$14 -> -1 | X14: =IF(A14>2,OFFSET(O14,-2,0),0)+S14 -> 200 | Y14: =M14 -> 3600
A15: =A14+1 -> 14 | B15: =Demand!B15 -> 24 | C15: =ROUNDUP(AVERAGE(B13,B14),0) -> 22 | D15: =3*C15 -> 66 | E15: =Distributor!J14 -> 0 | F15: =IF(A15=1,'Data Considered'!$B$5,Retailer!L14+Retailer!E15) -> 12 | G15: =F15+IF(A15>1,H14,0) -> 41 | H15: =IF(D15>G15,D15-G15,0) -> 25 | I15: =F15 -> 12 | J15: =MIN(I15,B15) -> 12 | K15: =B15-J15 -> 12 | L15: =I15-J15 -> 0 | M15: =J15*'Data Considered'!$B$7 -> 2160 | N15: =IF(A15>'Data Considered'!$B$13,OFFSET(Retailer!M15,-'Data Considered'!$B$13,0),0) -> 2160 | O15: =E15*'Data Considered'!$B$8 -> 0 | P15: =IF(A15>'Data Considered'!$B$14,OFFSET(Retailer!O15,-'Data Considered'!$B$14,0),0) -> 2520 | Q15: =N15-P15-T15-S15 -> -480 | R15: =IF(A15=1,'Data Considered'!$B$16,Retailer!R14+Retailer!Q15) -> 26410 | S15: =J15*'Data Considered'!$D$7 -> 120 | T15: =L15*'Data Considered'!$B$20 -> 0 | U15: =K15*'Data Considered'!$B$24 -> 480 | V15: =ROUNDUP(L15/$B$108,0) -> 0 | W15: =V15+'Data Considered'!$B$13-'Data Considered'!$B$14 -> -2 | X15: =IF(A15>2,OFFSET(O15,-2,0),0)+S15 -> 2640 | Y15: =M15 -> 2160
... A105: =A104+1 -> 104 | B105: =Demand!B105 -> 24 | C105: =ROUNDUP(AVERAGE(B103,B104),0) -> 27 | D105: =3*C105 -> 81 | E105: =Distributor!J104 -> 16 | F105: =IF(A105=1,'Data Considered'!$B$5,Retailer!L104+Retailer!E105) -> 16 | G105: =F105+IF(A105>1,H104,0) -> 69 | H105: =IF(D105>G105,D105-G105,0) -> 12 | I105: =F105 -> 16 | J105: =MIN(I105,B105) -> 16 | K105: =B105-J105 -> 8 | L105: =I105-J105 -> 0 | M105: =J105*'Data Considered'!$B$7 -> 2880 | N105: =IF(A105>'Data Considered'!$B$13,OFFSET(Retailer!M105,-'Data Considered'!$B$13,0),0) -> 2880 | O105: =E105*'Data Considered'!$B$8 -> 2240 | P105: =IF(A105>'Data Considered'!$B$14,OFFSET(Retailer!O105,-'Data Considered'!$B$14,0),0) -> 280 | Q105: =N105-P105-T105-S105 -> 2440 | R105: =IF(A105=1,'Data Considered'!$B$16,Retailer!R104+Retailer!Q105) -> 58040 | S105: =J105*'Data Considered'!$D$7 -> 160 | T105: =L105*'Data Considered'!$B$20 -> 0 | U105: =K105*'Data Considered'!$B$24 -> 320 | V105: =ROUNDUP(L105/$B$108,0) -> 0 | W105: =V105+'Data Considered'!$B$13-'Data Considered'!$B$14 -> -2 | X105: =IF(A105>2,OFFSET(O105,-2,0),0)+S105 -> 440 | Y105: =M105 -> 2880
B107: AVG DEMAND
B108: =AVERAGE(B2:B105) -> 20.471154
B110: VARIANCE DEMAND | H110: VARIANCE ORDER PLACED
B111: =_xlfn.VAR.S(B2:B105) -> 26.504014 | H111: =_xlfn.VAR.S(H2:H105) -> 164.36735

Sheet Distributor
A1: WEEK | B1: ORDERS FROM RETAILER | C1: FORECAST | D1: OUL | E1: GOODS RECEIVED | F1: BEGINNING INVENTORY | G1: INVENTORY POSITION | H1: ORDER PLACED TO MANUFACTURER | I1: GOODS AVAILABLE | J1: UNITS SOLD TO RETAILER | K1: LOST SALES | L1: ENDING INVENTORY | M1: INVOICE TO RETAILER | N1: PAYMENT RECEIVED | O1: PURCHASE COST | P1: PAYMENT MADE TO MANUFACTURER | Q1: NET CASH FLOW | R1: CASH POSITION | S1: OVERHEAD EXPENSES | T1: HOLDING COST | U1: SHORTAGE COST | V1: INVENTORY WEEKS | W1: CASH TO CASH CYCLE TIME | X1: ACCOUTS PAYABLE | Y1: ACCOUNTS RECEIVABLE
A2: 1 | B2: 0 | C2: 20 | D2: =3*C2 -> 60 | E2: =0 -> 0 | F2: =IF(A2=1,'Data Considered'!$B$5,Distributor!L1+Distributor!E2) -> 80 | G2: =F2+IF(A2>1,H1,0) -> 80 | H2: =IF(D2>G2,D2-G2,0) -> 0 | I2: =F2 -> 80 | J2: =MIN(I2,B2) -> 0 | K2: =B2-J2 -> 0 | L2: =I2-J2 -> 80 | M2: =J2*'Data Considered'!$B$9 -> 0 | N2: =Retailer!P2 -> 0 | O2: =E2*'Data Considered'!$B$10 -> 0 | P2: =IF(A2>'Data Considered'!$B$15,OFFSET(Distributor!O2,-'Data Considered'!$B$15,0),0) -> 0 | Q2: =N2-P2-T2-S2 -> -800 | R2: =IF(A2=1,'Data Considered'!$B$17,Distributor!R1+Distributor!Q2) -> 30000 | S2: =J2*'Data Considered'!$D$9 -> 0 | T2: =L2*'Data Considered'!$B$21 -> 800 | U2: =K2*'Data Considered'!$B$25 -> 0 | V2: =ROUNDUP(L2/$B$108,0) -> 5 | W2: =V2+'Data Considered'!$B$14-'Data Considered'!$B$15 -> 5 | X2: =IF(A2>2,OFFSET(O2,-2,0),0)+S2 -> 0 | Y2: =IF(A2>2,OFFSET(M2,-2,0),0) -> 0
A3: =A2+1 -> 2 | B3: =Retailer!H2 -> 0 | C3: =B2 -> 0 | D3: =3*C3 -> 0 | E3: =Manufacturer!J2 -> 0 | F3: =IF(A3=1,'Data Considered'!$B$5,Distributor!L2+Distributor!E3) -> 80 | G3: =F3+IF(A3>1,H2,0) -> 80 | H3: =IF(D3>G3,D3-G3,0) -> 0 | I3: =F3 -> 80 | J3: =MIN(I3,B3) -> 0 | K3: =B3-J3 -> 0 | L3: =I3-J3 -> 80 | M3: =J3*'Data Considered'!$B$9 -> 0 | N3: =Retailer!P3 -> 0 | O3: =E3*'Data Considered'!$B$10 -> 0 | P3: =IF(A3>'Data Considered'!$B$15,OFFSET(Distributor!O3,-'Data Considered'!$B$15,0),0) -> 0 | Q3: =N3-P3-T3-S3 -> -800 | R3: =IF(A3=1,'Data Considered'!$B$17,Distributor!R2+Distributor!Q3) -> 29200 | S3: =J3*'Data Considered'!$D$9 -> 0 | T3: =L3*'Data Considered'!$B$21 -> 800 | U3: =K3*'Data Considered'!$B$25 -> 0 | V3: =ROUNDUP(L3/$B$108,0) -> 5 | W3: =V3+'Data Considered'!$B$14-'Data Considered'!$B$15 -> 5 | X3: =IF(A3>2,OFFSET(O3,-2,0),0)+S3 -> 0 | Y3: =IF(A3>2,OFFSET(M3,-2,0),0) -> 0
A4: =A3+1 -> 3 | B4: =Retailer!H3 -> 20 | C4: =ROUNDUP(AVERAGE(Distributor!B2,Distributor!B3),0) -> 0 | D4: =3*C4 -> 0 | E4: =Manufacturer!J3 -> 0 | F4: =IF(A4=1,'Data Considered'!$B$5,Distributor!L3+Distributor!E4) -> 80 | G4: =F4+IF(A4>1,H3,0) -> 80 | H4: =IF(D4>G4,D4-G4,0) -> 0 | I4: =F4 -> 80 | J4: =MIN(I4,B4) -> 20 | K4: =B4-J4 -> 0 | L4: =I4-J4 -> 60 | M4: =J4*'Data Considered'!$B$9 -> 2800 | N4: =Retailer!P4 -> 0 | O4: =E4*'Data Considered'!$B$10 -> 0 | P4: =IF(A4>'Data Considered'!$B$15,OFFSET(Distributor!O4,-'Data Considered'!$B$15,0),0) -> 0 | Q4: =N4-P4-T4-S4 -> -740 | R4: =IF(A4=1,'Data Considered'!$B$17,Distributor!R3+Distributor!Q4) -> 28460 | S4: =J4*'Data Considered'!$D$9 -> 140 | T4: =L4*'Data Considered'!$B$21 -> 600 | U4: =K4*'Data Considered'!$B$25 -> 0 | V4: =ROUNDUP(L4/$B$108,0) -> 4 | W4: =V4+'Data Considered'!$B$14-'Data Considered'!$B$15 -> 4 | X4: =IF(A4>2,OFFSET(O4,-2,0),0)+S4 -> 140 | Y4: =IF(A4>2,OFFSET(M4,-2,0),0) -> 0
A5: =A4+1 -> 4 | B5: =Retailer!H4 -> 24 | C5: =ROUNDUP(AVERAGE(Distributor!B3,Distributor!B4),0) -> 10 | D5: =3*C5 -> 30 | E5: =Manufacturer!J4 -> 0 | F5: =IF(A5=1,'Data Considered'!$B$5,Distributor!L4+Distributor!E5) -> 60 | G5: =F5+IF(A5>1,H4,0) -> 60 | H5: =IF(D5>G5,D5-G5,0) -> 0 | I5: =F5 -> 60 | J5: =MIN(I5,B5) -> 24 | K5: =B5-J5 -> 0 | L5: =I5-J5 -> 36 | M5: =J5*'Data Considered'!$B$9 -> 3360 | N5: =Retailer!P5 -> 0 | O5: =E5*'Data Considered'!$B$10 -> 0 | P5: =IF(A5>'Data Considered'!$B$15,OFFSET(Distributor!O5,-'Data Considered'!$B$15,0),0) -> 0 | Q5: =N5-P5-T5-S5 -> -528 | R5: =IF(A5=1,'Data Considered'!$B$17,Distributor!R4+Distributor!Q5) -> 27932 | S5: =J5*'Data Considered'!$D$9 -> 168 | T5: =L5*'Data Considered'!$B$21 -> 360 | U5: =K5*'Data Considered'!$B$25 -> 0 | V5: =ROUNDUP(L5/$B$108,0) -> 2 | W5: =V5+'Data Considered'!$B$14-'Data Considered'!$B$15 -> 2 | X5: =IF(A5>2,OFFSET(O5,-2,0),0)+S5 -> 168 | Y5: =IF(A5>2,OFFSET(M5,-2,0),0) -> 0
A6: =A5+1 -> 5 | B6: =Retailer!H5 -> 0 | C6: =ROUNDUP(AVERAGE(Distributor!B4,Distributor!B5),0) -> 22 | D6: =3*C6 -> 66 | E6: =Manufacturer!J5 -> 0 | F6: =IF(A6=1,'Data Considered'!$B$5,Distributor!L5+Distributor!E6) -> 36 | G6: =F6+IF(A6>1,H5,0) -> 36 | H6: =IF(D6>G6,D6-G6,0) -> 30 | I6: =F6 -> 36 | J6: =MIN(I6,B6) -> 0 | K6: =B6-J6 -> 0 | L6: =I6-J6 -> 36 | M6: =J6*'Data Considered'!$B$9 -> 0 | N6: =Retailer!P6 -> 0 | O6: =E6*'Data Considered'!$B$10 -> 0 | P6: =IF(A6>'Data Considered'!$B$15,OFFSET(Distributor!O6,-'Data Considered'!$B$15,0),0) -> 0 | Q6: =N6-P6-T6-S6 -> -360 | R6: =IF(A6=1,'Data Considered'!$B$17,Distributor!R5+Distributor!Q6) -> 27572 | S6: =J6*'Data Considered'!$D$9 -> 0 | T6: =L6*'Data Considered'!$B$21 -> 360 | U6: =K6*'Data Considered'!$B$25 -> 0 | V6: =ROUNDUP(L6/$B$108,0) -> 2 | W6: =V6+'Data Considered'!$B$14-'Data Considered'!$B$15 -> 2 | X6: =IF(A6>2,OFFSET(O6,-2,0),0)+S6 -> 0 | Y6: =IF(A6>2,OFFSET(M6,-2,0),0) -> 2800
A7: =A6+1 -> 6 | B7: =Retailer!H6 -> 15 | C7: =ROUNDUP(AVERAGE(Distributor!B5,Distributor!B6),0) -> 12 | D7: =3*C7 -> 36 | E7: =Manufacturer!J6 -> 0 | F7: =IF(A7=1,'Data Considered'!$B$5,Distributor!L6+Distributor!E7) -> 36 | G7: =F7+IF(A7>1,H6,0) -> 66 | H7: =IF(D7>G7,D7-G7,0) -> 0 | I7: =F7 -> 36 | J7: =MIN(I7,B7) -> 15 | K7: =B7-J7 -> 0 | L7: =I7-J7 -> 21 | M7: =J7*'Data Considered'!$B$9 -> 2100 | N7: =Retailer!P7 -> 2800 | O7: =E7*'Data Considered'!$B$10 -> 0 | P7: =IF(A7>'Data Considered'!$B$15,OFFSET(Distributor!O7,-'Data Considered'!$B$15,0),0) -> 0 | Q7: =N7-P7-T7-S7 -> 2485 | R7: =IF(A7=1,'Data Considered'!$B$17,Distributor!R6+Distributor!Q7) -> 30057 | S7: =J7*'Data Considered'!$D$9 -> 105 | T7: =L7*'Data Considered'!$B$21 -> 210 | U7: =K7*'Data Considered'!$B$25 -> 0 | V7: =ROUNDUP(L7/$B$108,0) -> 2 | W7: =V7+'Data Considered'!$B$14-'Data Considered'!$B$15 -> 2 | X7: =IF(A7>2,OFFSET(O7,-2,0),0)+S7 -> 105 | Y7: =IF(A7>2,OFFSET(M7,-2,0),0) -> 3360
A8: =A7+1 -> 7 | B8: =Retailer!H7 -> 44 | C8: =ROUNDUP(AVERAGE(Distributor!B6,Distributor!B7),0) -> 8 | D8: =3*C8 -> 24 | E8: =Manufacturer!J7 -> 30 | F8: =IF(A8=1,'Data Considered'!$B$5,Distributor!L7+Distributor!E8) -> 51 | G8: =F8+IF(A8>1,H7,0) -> 51 | H8: =IF(D8>G8,D8-G8,0) -> 0 | I8: =F8 -> 51 | J8: =MIN(I8,B8) -> 44 | K8: =B8-J8 -> 0 | L8: =I8-J8 -> 7 | M8: =J8*'Data Considered'!$B$9 -> 6160 | N8: =Retailer!P8 -> 3360 | O8: =E8*'Data Considered'!$B$10 -> 3000 | P8: =IF(A8>'Data Considered'!$B$15,OFFSET(Distributor!O8,-'Data Considered'!$B$15,0),0) -> 0 | Q8: =N8-P8-T8-S8 -> 2982 | R8: =IF(A8=1,'Data Considered'!$B$17,Distributor!R7+Distributor!Q8) -> 33039 | S8: =J8*'Data Considered'!$D$9 -> 308 | T8: =L8*'Data Considered'!$B$21 -> 70 | U8: =K8*'Data Considered'!$B$25 -> 0 | V8: =ROUNDUP(L8/$B$108,0) -> 1 | W8: =V8+'Data Considered'!$B$14-'Data Considered'!$B$15 -> 1 | X8: =IF(A8>2,OFFSET(O8,-2,0),0)+S8 -> 308 | Y8: =IF(A8>2,OFFSET(M8,-2,0),0) -> 0
A9: =A8+1 -> 8 | B9: =Retailer!H8 -> 16 | C9: =ROUNDUP(AVERAGE(Distributor!B7,Distributor!B8),0) -> 30 | D9: =3*C9 -> 90 | E9: =Manufacturer!J8 -> 0 | F9: =IF(A9=1,'Data Considered'!$B$5,Distributor!L8+Distributor!E9) -> 7 | G9: =F9+IF(A9>1,H8,0) -> 7 | H9: =IF(D9>G9,D9-G9,0) -> 83 | I9: =F9 -> 7 | J9: =MIN(I9,B9) -> 7 | K9: =B9-J9 -> 9 | L9: =I9-J9 -> 0 | M9: =J9*'Data Considered'!$B$9 -> 980 | N9: =Retailer!P9 -> 0 | O9: =E9*'Data Considered'!$B$10 -> 0 | P9: =IF(A9>'Data Considered'!$B$15,OFFSET(Distributor!O9,-'Data Considered'!$B$15,0),0) -> 0 | Q9: =N9-P9-T9-S9 -> -49 | R9: =IF(A9=1,'Data Considered'!$B$17,Distributor!R8+Distributor!Q9) -> 32990 | S9: =J9*'Data Considered'!$D$9 -> 49 | T9: =L9*'Data Considered'!$B$21 -> 0 | U9: =K9*'Data Considered'!$B$25 -> 270 | V9: =ROUNDUP(L9/$B$108,0) -> 0 | W9: =V9+'Data Considered'!$B$14-'Data Considered'!$B$15 -> 0 | X9: =IF(A9>2,OFFSET(O9,-2,0),0)+S9 -> 49 | Y9: =IF(A9>2,OFFSET(M9,-2,0),0) -> 2100
A10: =A9+1 -> 9 | B10: =Retailer!H9 -> 15 | C10: =ROUNDUP(AVERAGE(Distributor!B8,Distributor!B9),0) -> 30 | D10: =3*C10 -> 90 | E10: =Manufacturer!J9 -> 0 | F10: =IF(A10=1,'Data Considered'!$B$5,Distributor!L9+Distributor!E10) -> 0 | G10: =F10+IF(A10>1,H9,0) -> 83 | H10: =IF(D10>G10,D10-G10,0) -> 7 | I10: =F10 -> 0 | J10: =MIN(I10,B10) -> 0 | K10: =B10-J10 -> 15 | L10: =I10-J10 -> 0 | M10: =J10*'Data Considered'!$B$9 -> 0 | N10: =Retailer!P10 -> 2100 | O10: =E10*'Data Considered'!$B$10 -> 0 | P10: =IF(A10>'Data Considered'!$B$15,OFFSET(Distributor!O10,-'Data Considered'!$B$15,0),0) -> 3000 | Q10: =N10-P10-T10-S10 -> -900 | R10: =IF(A10=1,'Data Considered'!$B$17,Distributor!R9+Distributor!Q10) -> 32090 | S10: =J10*'Data Considered'!$D$9 -> 0 | T10: =L10*'Data Considered'!$B$21 -> 0 | U10: =K10*'Data Considered'!$B$25 -> 450 | V10: =ROUNDUP(L10/$B$108,0) -> 0 | W10: =V10+'Data Considered'!$B$14-'Data Considered'!$B$15 -> 0 | X10: =IF(A10>2,OFFSET(O10,-2,0),0)+S10 -> 3000 | Y10: =IF(A10>2,OFFSET(M10,-2,0),0) -> 6160
A11: =A10+1 -> 10 | B11: =Retailer!H10 -> 0 | C11: =ROUNDUP(AVERAGE(Distributor!B9,Distributor!B10),0) -> 16 | D11: =3*C11 -> 48 | E11: =Manufacturer!J10 -> 50 | F11: =IF(A11=1,'Data Considered'!$B$5,Distributor!L10+Distributor!E11) -> 50 | G11: =F11+IF(A11>1,H10,0) -> 57 | H11: =IF(D11>G11,D11-G11,0) -> 0 | I11: =F11 -> 50 | J11: =MIN(I11,B11) -> 0 | K11: =B11-J11 -> 0 | L11: =I11-J11 -> 50 | M11: =J11*'Data Considered'!$B$9 -> 0 | N11: =Retailer!P11 -> 6160 | O11: =E11*'Data Considered'!$B$10 -> 5000 | P11: =IF(A11>'Data Considered'!$B$15,OFFSET(Distributor!O11,-'Data Considered'!$B$15,0),0) -> 0 | Q11: =N11-P11-T11-S11 -> 5660 | R11: =IF(A11=1,'Data Considered'!$B$17,Distributor!R10+Distributor!Q11) -> 37750 | S11: =J11*'Data Considered'!$D$9 -> 0 | T11: =L11*'Data Considered'!$B$21 -> 500 | U11: =K11*'Data Considered'!$B$25 -> 0 | V11: =ROUNDUP(L11/$B$108,0) -> 3 | W11: =V11+'Data Considered'!$B$14-'Data Considered'!$B$15 -> 3 | X11: =IF(A11>2,OFFSET(O11,-2,0),0)+S11 -> 0 | Y11: =IF(A11>2,OFFSET(M11,-2,0),0) -> 980
A12: =A11+1 -> 11 | B12: =Retailer!H11 -> 18 | C12: =ROUNDUP(AVERAGE(Distributor!B10,Distributor!B11),0) -> 8 | D12: =3*C12 -> 24 | E12: =Manufacturer!J11 -> 0 | F12: =IF(A12=1,'Data Considered'!$B$5,Distributor!L11+Distributor!E12) -> 50 | G12: =F12+IF(A12>1,H11,0) -> 50 | H12: =IF(D12>G12,D12-G12,0) -> 0 | I12: =F12 -> 50 | J12: =MIN(I12,B12) -> 18 | K12: =B12-J12 -> 0 | L12: =I12-J12 -> 32 | M12: =J12*'Data Considered'!$B$9 -> 2520 | N12: =Retailer!P12 -> 980 | O12: =E12*'Data Considered'!$B$10 -> 0 | P12: =IF(A12>'Data Considered'!$B$15,OFFSET(Distributor!O12,-'Data Considered'!$B$15,0),0) -> 0 | Q12: =N12-P12-T12-S12 -> 534 | R12: =IF(A12=1,'Data Considered'!$B$17,Distributor!R11+Distributor!Q12) -> 38284 | S12: =J12*'Data Considered'!$D$9 -> 126 | T12: =L12*'Data Considered'!$B$21 -> 320 | U12: =K12*'Data Considered'!$B$25 -> 0 | V12: =ROUNDUP(L12/$B$108,0) -> 2 | W12: =V12+'Data Considered'!$B$14-'Data Considered'!$B$15 -> 2 | X12: =IF(A12>2,OFFSET(O12,-2,0),0)+S12 -> 126 | Y12: =IF(A12>2,OFFSET(M12,-2,0),0) -> 0
A13: =A12+1 -> 12 | B13: =Retailer!H12 -> 40 | C13: =ROUNDUP(AVERAGE(Distributor!B11,Distributor!B12),0) -> 9 | D13: =3*C13 -> 27 | E13: =Manufacturer!J12 -> 0 | F13: =IF(A13=1,'Data Considered'!$B$5,Distributor!L12+Distributor!E13) -> 32 | G13: =F13+IF(A13>1,H12,0) -> 32 | H13: =IF(D13>G13,D13-G13,0) -> 0 | I13: =F13 -> 32 | J13: =MIN(I13,B13) -> 32 | K13: =B13-J13 -> 8 | L13: =I13-J13 -> 0 | M13: =J13*'Data Considered'!$B$9 -> 4480 | N13: =Retailer!P13 -> 0 | O13: =E13*'Data Considered'!$B$10 -> 0 | P13: =IF(A13>'Data Considered'!$B$15,OFFSET(Distributor!O13,-'Data Considered'!$B$15,0),0) -> 5000 | Q13: =N13-P13-T13-S13 -> -5224 | R13: =IF(A13=1,'Data Considered'!$B$17,Distributor!R12+Distributor!Q13) -> 33060 | S13: =J13*'Data Considered'!$D$9 -> 224 | T13: =L13*'Data Considered'!$B$21 -> 0 | U13: =K13*'Data Considered'!$B$25 -> 240 | V13: =ROUNDUP(L13/$B$108,0) -> 0 | W13: =V13+'Data Considered'!$B$14-'Data Considered'!$B$15 -> 0 | X13: =IF(A13>2,OFFSET(O13,-2,0),0)+S13 -> 5224 | Y13: =IF(A13>2,OFFSET(M13,-2,0),0) -> 0
A14: =A13+1 -> 13 | B14: =Retailer!H13 -> 11 | C14: =ROUNDUP(AVERAGE(Distributor!B12,Distributor!B13),0) -> 29 | D14: =3*C14 -> 87 | E14: =Manufacturer!J13 -> 0 | F14: =IF(A14=1,'Data Considered'!$B$5,Distributor!L13+Distributor!E14) -> 0 | G14: =F14+IF(A14>1,H13,0) -> 0 | H14: =IF(D14>G14,D14-G14,0) -> 87 | I14: =F14 -> 0 | J14: =MIN(I14,B14) -> 0 | K14: =B14-J14 -> 11 | L14: =I14-J14 -> 0 | M14: =J14*'Data Considered'!$B$9 -> 0 | N14: =Retailer!P14 -> 0 | O14: =E14*'Data Considered'!$B$10 -> 0 | P14: =IF(A14>'Data Considered'!$B$15,OFFSET(Distributor!O14,-'Data Considered'!$B$15,0),0) -> 0 | Q14: =N14-P14-T14-S14 -> 0 | R14: =IF(A14=1,'Data Considered'!$B$17,Distributor!R13+Distributor!Q14) -> 33060 | S14: =J14*'Data Considered'!$D$9 -> 0 | T14: =L14*'Data Considered'!$B$21 -> 0 | U14: =K14*'Data Considered'!$B$25 -> 330 | V14: =ROUNDUP(L14/$B$108,0) -> 0 | W14: =V14+'Data Considered'!$B$14-'Data Considered'!$B$15 -> 0 | X14: =IF(A14>2,OFFSET(O14,-2,0),0)+S14 -> 0 | Y14: =IF(A14>2,OFFSET(M14,-2,0),0) -> 2520
A15: =A14+1 -> 14 | B15: =Retailer!H14 -> 29 | C15: =ROUNDUP(AVERAGE(Distributor!B13,Distributor!B14),0) -> 26 | D15: =3*C15 -> 78 | E15: =Manufacturer!J14 -> 0 | F15: =IF(A15=1,'Data Considered'!$B$5,Distributor!L14+Distributor!E15) -> 0 | G15: =F15+IF(A15>1,H14,0) -> 87 | H15: =IF(D15>G15,D15-G15,0) -> 0 | I15: =F15 -> 0 | J15: =MIN(I15,B15) -> 0 | K15: =B15-J15 -> 29 | L15: =I15-J15 -> 0 | M15: =J15*'Data Considered'!$B$9 -> 0 | N15: =Retailer!P15 -> 2520 | O15: =E15*'Data Considered'!$B$10 -> 0 | P15: =IF(A15>'Data Considered'!$B$15,OFFSET(Distributor!O15,-'Data Considered'!$B$15,0),0) -> 0 | Q15: =N15-P15-T15-S15 -> 2520 | R15: =IF(A15=1,'Data Considered'!$B$17,Distributor!R14+Distributor!Q15) -> 35580 | S15: =J15*'Data Considered'!$D$9 -> 0 | T15: =L15*'Data Considered'!$B$21 -> 0 | U15: =K15*'Data Considered'!$B$25 -> 870 | V15: =ROUNDUP(L15/$B$108,0) -> 0 | W15: =V15+'Data Considered'!$B$14-'Data Considered'!$B$15 -> 0 | X15: =IF(A15>2,OFFSET(O15,-2,0),0)+S15 -> 0 | Y15: =IF(A15>2,OFFSET(M15,-2,0),0) -> 4480
... A105: =A104+1 -> 104 | B105: =Retailer!H104 -> 53 | C105: =ROUNDUP(AVERAGE(Distributor!B103,Distributor!B104),0) -> 11 | D105: =3*C105 -> 33 | E105: =Manufacturer!J104 -> 0 | F105: =IF(A105=1,'Data Considered'!$B$5,Distributor!L104+Distributor!E105) -> 60 | G105: =F105+IF(A105>1,H104,0) -> 60 | H105: =IF(D105>G105,D105-G105,0) -> 0 | I105: =F105 -> 60 | J105: =MIN(I105,B105) -> 53 | K105: =B105-J105 -> 0 | L105: =I105-J105 -> 7 | M105: =J105*'Data Considered'!$B$9 -> 7420 | N105: =Retailer!P105 -> 280 | O105: =E105*'Data Considered'!$B$10 -> 0 | P105: =IF(A105>'Data Considered'!$B$15,OFFSET(Distributor!O105,-'Data Considered'!$B$15,0),0) -> 4800 | Q105: =N105-P105-T105-S105 -> -4961 | R105: =IF(A105=1,'Data Considered'!$B$17,Distributor!R104+Distributor!Q105) -> 59177 | S105: =J105*'Data Considered'!$D$9 -> 371 | T105: =L105*'Data Considered'!$B$21 -> 70 | U105: =K105*'Data Considered'!$B$25 -> 0 | V105: =ROUNDUP(L105/$B$108,0) -> 1 | W105: =V105+'Data Considered'!$B$14-'Data Considered'!$B$15 -> 1 | X105: =IF(A105>2,OFFSET(O105,-2,0),0)+S105 -> 5171 | Y105: =IF(A105>2,OFFSET(M105,-2,0),0) -> 840
B107: AVG DEMAND
B108: =AVERAGE(B2:B105) -> 18.778846
B110: VARIANCE DEMAND | H110: VARIANCE ORDER
B111: =_xlfn.VAR.S(B2:B105) -> 167.35838 | H111: =_xlfn.VAR.S(H2:H105) -> 615.2598

Sheet Manufacturer
A1: WEEK | B1: ORDERS FROM DISTRIBUTOR | C1: FORECAST | D1: OUL | E1: GOODS PRODUCED | F1: BEGINNING INVENTORY | G1: INVENTORY POSITION | H1: ORDER PLACED FOR PRODUCTION | I1: GOODS AVAILABLE | J1: UNITS SHIPPED TO DISTRIBUTOR | K1: LOST SALES | L1: ENDING INVENTORY | M1: INVOICE TO DISTRIBUTOR | N1: PAYMENT RECEIVED | O1: PRODUCTION COST | P1: NET CASH FLOW | Q1: CASH POSITION | R1: OVERHEAD EXPENSES | S1: HOLDING COST | T1: SHORTAGE COST | U1: INVENTORY WEEKS | V1: CASH TO CASH CYCLE TIME | W1: ACCOUNTS PAYABLE | X1: ACCOUNTS RECEIVABLE
A2: 1 | B2: =0 -> 0 | C2: 20 | D2: =3*C2 -> 60 | E2: =IF(A2>2,OFFSET(H2,-2,0),0) -> 0 | F2: =IF(A2=1,'Data Considered'!$B$5,L1+E2) -> 80 | G2: =F2+IF(A2>1,H1,0) -> 80 | H2: =IF(D2>G2,D2-G2,0) -> 0 | I2: =F2 -> 80 | J2: =MIN(B2,I2) -> 0 | K2: =B2-J2 -> 0 | L2: =I2-J2 -> 80 | M2: =J2*'Data Considered'!$B$11 -> 0 | N2: =Distributor!P2 -> 0 | O2: =H2*'Data Considered'!$B$12 -> 0 | P2: =N2-O2-S2-R2 -> -400 | Q2: =IF(A2=1,'Data Considered'!$B$18,Manufacturer!Q1+Manufacturer!P2) -> 50000 | R2: =J2*'Data Considered'!$D$11 -> 0 | S2: =L2*'Data Considered'!$B$22 -> 400 | T2: =K2*'Data Considered'!$B$26 -> 0 | U2: =ROUNDUP(L2/$B$108,0) -> 5 | V2: =U2+'Data Considered'!$B$15-0 -> 7 | W2: =O2+R2 -> 0 | X2: =IF(A2>2,OFFSET(M2,-2,0),0) -> 0
A3: =A2+1 -> 2 | B3: =Distributor!H2 -> 0 | C3: =B2 -> 0 | D3: =3*C3 -> 0 | E3: =IF(A3>2,OFFSET(H3,-2,0),0) -> 0 | F3: =IF(A3=1,'Data Considered'!$B$5,L2+E3) -> 80 | G3: =F3+IF(A3>1,H2,0) -> 80 | H3: =IF(D3>G3,D3-G3,0) -> 0 | I3: =F3 -> 80 | J3: =MIN(B3,I3) -> 0 | K3: =B3-J3 -> 0 | L3: =I3-J3 -> 80 | M3: =J3*'Data Considered'!$B$11 -> 0 | N3: =Distributor!P3 -> 0 | O3: =H3*'Data Considered'!$B$12 -> 0 | P3: =N3-O3-S3-R3 -> -400 | Q3: =IF(A3=1,'Data Considered'!$B$18,Manufacturer!Q2+Manufacturer!P3) -> 49600 | R3: =J3*'Data Considered'!$D$11 -> 0 | S3: =L3*'Data Considered'!$B$22 -> 400 | T3: =K3*'Data Considered'!$B$26 -> 0 | U3: =ROUNDUP(L3/$B$108,0) -> 5 | V3: =U3+'Data Considered'!$B$15-0 -> 7 | W3: =O3+R3 -> 0 | X3: =IF(A3>2,OFFSET(M3,-2,0),0) -> 0
A4: =A3+1 -> 3 | B4: =Distributor!H3 -> 0 | C4: =ROUNDUP(AVERAGE(B2,B3),0) -> 0 | D4: =3*C4 -> 0 | E4: =IF(A4>2,OFFSET(H4,-2,0),0) -> 0 | F4: =IF(A4=1,'Data Considered'!$B$5,L3+E4) -> 80 | G4: =F4+IF(A4>1,H3,0) -> 80 | H4: =IF(D4>G4,D4-G4,0) -> 0 | I4: =F4 -> 80 | J4: =MIN(B4,I4) -> 0 | K4: =B4-J4 -> 0 | L4: =I4-J4 -> 80 | M4: =J4*'Data Considered'!$B$11 -> 0 | N4: =Distributor!P4 -> 0 | O4: =H4*'Data Considered'!$B$12 -> 0 | P4: =N4-O4-S4-R4 -> -400 | Q4: =IF(A4=1,'Data Considered'!$B$18,Manufacturer!Q3+Manufacturer!P4) -> 49200 | R4: =J4*'Data Considered'!$D$11 -> 0 | S4: =L4*'Data Considered'!$B$22 -> 400 | T4: =K4*'Data Considered'!$B$26 -> 0 | U4: =ROUNDUP(L4/$B$108,0) -> 5 | V4: =U4+'Data Considered'!$B$15-0 -> 7 | W4: =O4+R4 -> 0 | X4: =IF(A4>2,OFFSET(M4,-2,0),0) -> 0
A5: =A4+1 -> 4 | B5: =Distributor!H4 -> 0 | C5: =ROUNDUP(AVERAGE(B3,B4),0) -> 0 | D5: =3*C5 -> 0 | E5: =IF(A5>2,OFFSET(H5,-2,0),0) -> 0 | F5: =IF(A5=1,'Data Considered'!$B$5,L4+E5) -> 80 | G5: =F5+IF(A5>1,H4,0) -> 80 | H5: =IF(D5>G5,D5-G5,0) -> 0 | I5: =F5 -> 80 | J5: =MIN(B5,I5) -> 0 | K5: =B5-J5 -> 0 | L5: =I5-J5 -> 80 | M5: =J5*'Data Considered'!$B$11 -> 0 | N5: =Distributor!P5 -> 0 | O5: =H5*'Data Considered'!$B$12 -> 0 | P5: =N5-O5-S5-R5 -> -400 | Q5: =IF(A5=1,'Data Considered'!$B$18,Manufacturer!Q4+Manufacturer!P5) -> 48800 | R5: =J5*'Data Considered'!$D$11 -> 0 | S5: =L5*'Data Considered'!$B$22 -> 400 | T5: =K5*'Data Considered'!$B$26 -> 0 | U5: =ROUNDUP(L5/$B$108,0) -> 5 | V5: =U5+'Data Considered'!$B$15-0 -> 7 | W5: =O5+R5 -> 0 | X5: =IF(A5>2,OFFSET(M5,-2,0),0) -> 0
A6: =A5+1 -> 5 | B6: =Distributor!H5 -> 0 | C6: =ROUNDUP(AVERAGE(B4,B5),0) -> 0 | D6: =3*C6 -> 0 | E6: =IF(A6>2,OFFSET(H6,-2,0),0) -> 0 | F6: =IF(A6=1,'Data Considered'!$B$5,L5+E6) -> 80 | G6: =F6+IF(A6>1,H5,0) -> 80 | H6: =IF(D6>G6,D6-G6,0) -> 0 | I6: =F6 -> 80 | J6: =MIN(B6,I6) -> 0 | K6: =B6-J6 -> 0 | L6: =I6-J6 -> 80 | M6: =J6*'Data Considered'!$B$11 -> 0 | N6: =Distributor!P6 -> 0 | O6: =H6*'Data Considered'!$B$12 -> 0 | P6: =N6-O6-S6-R6 -> -400 | Q6: =IF(A6=1,'Data Considered'!$B$18,Manufacturer!Q5+Manufacturer!P6) -> 48400 | R6: =J6*'Data Considered'!$D$11 -> 0 | S6: =L6*'Data Considered'!$B$22 -> 400 | T6: =K6*'Data Considered'!$B$26 -> 0 | U6: =ROUNDUP(L6/$B$108,0) -> 5 | V6: =U6+'Data Considered'!$B$15-0 -> 7 | W6: =O6+R6 -> 0 | X6: =IF(A6>2,OFFSET(M6,-2,0),0) -> 0
A7: =A6+1 -> 6 | B7: =Distributor!H6 -> 30 | C7: =ROUNDUP(AVERAGE(B5,B6),0) -> 0 | D7: =3*C7 -> 0 | E7: =IF(A7>2,OFFSET(H7,-2,0),0) -> 0 | F7: =IF(A7=1,'Data Considered'!$B$5,L6+E7) -> 80 | G7: =F7+IF(A7>1,H6,0) -> 80 | H7: =IF(D7>G7,D7-G7,0) -> 0 | I7: =F7 -> 80 | J7: =MIN(B7,I7) -> 30 | K7: =B7-J7 -> 0 | L7: =I7-J7 -> 50 | M7: =J7*'Data Considered'!$B$11 -> 3000 | N7: =Distributor!P7 -> 0 | O7: =H7*'Data Considered'!$B$12 -> 0 | P7: =N7-O7-S7-R7 -> -400 | Q7: =IF(A7=1,'Data Considered'!$B$18,Manufacturer!Q6+Manufacturer!P7) -> 48000 | R7: =J7*'Data Considered'!$D$11 -> 150 | S7: =L7*'Data Considered'!$B$22 -> 250 | T7: =K7*'Data Considered'!$B$26 -> 0 | U7: =ROUNDUP(L7/$B$108,0) -> 4 | V7: =U7+'Data Considered'!$B$15-0 -> 6 | W7: =O7+R7 -> 150 | X7: =IF(A7>2,OFFSET(M7,-2,0),0) -> 0
A8: =A7+1 -> 7 | B8: =Distributor!H7 -> 0 | C8: =ROUNDUP(AVERAGE(B6,B7),0) -> 15 | D8: =3*C8 -> 45 | E8: =IF(A8>2,OFFSET(H8,-2,0),0) -> 0 | F8: =IF(A8=1,'Data Considered'!$B$5,L7+E8) -> 50 | G8: =F8+IF(A8>1,H7,0) -> 50 | H8: =IF(D8>G8,D8-G8,0) -> 0 | I8: =F8 -> 50 | J8: =MIN(B8,I8) -> 0 | K8: =B8-J8 -> 0 | L8: =I8-J8 -> 50 | M8: =J8*'Data Considered'!$B$11 -> 0 | N8: =Distributor!P8 -> 0 | O8: =H8*'Data Considered'!$B$12 -> 0 | P8: =N8-O8-S8-R8 -> -250 | Q8: =IF(A8=1,'Data Considered'!$B$18,Manufacturer!Q7+Manufacturer!P8) -> 47750 | R8: =J8*'Data Considered'!$D$11 -> 0 | S8: =L8*'Data Considered'!$B$22 -> 250 | T8: =K8*'Data Considered'!$B$26 -> 0 | U8: =ROUNDUP(L8/$B$108,0) -> 4 | V8: =U8+'Data Considered'!$B$15-0 -> 6 | W8: =O8+R8 -> 0 | X8: =IF(A8>2,OFFSET(M8,-2,0),0) -> 0
A9: =A8+1 -> 8 | B9: =Distributor!H8 -> 0 | C9: =ROUNDUP(AVERAGE(B7,B8),0) -> 15 | D9: =3*C9 -> 45 | E9: =IF(A9>2,OFFSET(H9,-2,0),0) -> 0 | F9: =IF(A9=1,'Data Considered'!$B$5,L8+E9) -> 50 | G9: =F9+IF(A9>1,H8,0) -> 50 | H9: =IF(D9>G9,D9-G9,0) -> 0 | I9: =F9 -> 50 | J9: =MIN(B9,I9) -> 0 | K9: =B9-J9 -> 0 | L9: =I9-J9 -> 50 | M9: =J9*'Data Considered'!$B$11 -> 0 | N9: =Distributor!P9 -> 0 | O9: =H9*'Data Considered'!$B$12 -> 0 | P9: =N9-O9-S9-R9 -> -250 | Q9: =IF(A9=1,'Data Considered'!$B$18,Manufacturer!Q8+Manufacturer!P9) -> 47500 | R9: =J9*'Data Considered'!$D$11 -> 0 | S9: =L9*'Data Considered'!$B$22 -> 250 | T9: =K9*'Data Considered'!$B$26 -> 0 | U9: =ROUNDUP(L9/$B$108,0) -> 4 | V9: =U9+'Data Considered'!$B$15-0 -> 6 | W9: =O9+R9 -> 0 | X9: =IF(A9>2,OFFSET(M9,-2,0),0) -> 3000
A10: =A9+1 -> 9 | B10: =Distributor!H9 -> 83 | C10: =ROUNDUP(AVERAGE(B8,B9),0) -> 0 | D10: =3*C10 -> 0 | E10: =IF(A10>2,OFFSET(H10,-2,0),0) -> 0 | F10: =IF(A10=1,'Data Considered'!$B$5,L9+E10) -> 50 | G10: =F10+IF(A10>1,H9,0) -> 50 | H10: =IF(D10>G10,D10-G10,0) -> 0 | I10: =F10 -> 50 | J10: =MIN(B10,I10) -> 50 | K10: =B10-J10 -> 33 | L10: =I10-J10 -> 0 | M10: =J10*'Data Considered'!$B$11 -> 5000 | N10: =Distributor!P10 -> 3000 | O10: =H10*'Data Considered'!$B$12 -> 0 | P10: =N10-O10-S10-R10 -> 2750 | Q10: =IF(A10=1,'Data Considered'!$B$18,Manufacturer!Q9+Manufacturer!P10) -> 50250 | R10: =J10*'Data Considered'!$D$11 -> 250 | S10: =L10*'Data Considered'!$B$22 -> 0 | T10: =K10*'Data Considered'!$B$26 -> 1320 | U10: =ROUNDUP(L10/$B$108,0) -> 0 | V10: =U10+'Data Considered'!$B$15-0 -> 2 | W10: =O10+R10 -> 250 | X10: =IF(A10>2,OFFSET(M10,-2,0),0) -> 0
A11: =A10+1 -> 10 | B11: =Distributor!H10 -> 7 | C11: =ROUNDUP(AVERAGE(B9,B10),0) -> 42 | D11: =3*C11 -> 126 | E11: =IF(A11>2,OFFSET(H11,-2,0),0) -> 0 | F11: =IF(A11=1,'Data Considered'!$B$5,L10+E11) -> 0 | G11: =F11+IF(A11>1,H10,0) -> 0 | H11: =IF(D11>G11,D11-G11,0) -> 126 | I11: =F11 -> 0 | J11: =MIN(B11,I11) -> 0 | K11: =B11-J11 -> 7 | L11: =I11-J11 -> 0 | M11: =J11*'Data Considered'!$B$11 -> 0 | N11: =Distributor!P11 -> 0 | O11: =H11*'Data Considered'!$B$12 -> 6300 | P11: =N11-O11-S11-R11 -> -6300 | Q11: =IF(A11=1,'Data Considered'!$B$18,Manufacturer!Q10+Manufacturer!P11) -> 43950 | R11: =J11*'Data Considered'!$D$11 -> 0 | S11: =L11*'Data Considered'!$B$22 -> 0 | T11: =K11*'Data Considered'!$B$26 -> 280 | U11: =ROUNDUP(L11/$B$108,0) -> 0 | V11: =U11+'Data Considered'!$B$15-0 -> 2 | W11: =O11+R11 -> 6300 | X11: =IF(A11>2,OFFSET(M11,-2,0),0) -> 0
A12: =A11+1 -> 11 | B12: =Distributor!H11 -> 0 | C12: =ROUNDUP(AVERAGE(B10,B11),0) -> 45 | D12: =3*C12 -> 135 | E12: =IF(A12>2,OFFSET(H12,-2,0),0) -> 0 | F12: =IF(A12=1,'Data Considered'!$B$5,L11+E12) -> 0 | G12: =F12+IF(A12>1,H11,0) -> 126 | H12: =IF(D12>G12,D12-G12,0) -> 9 | I12: =F12 -> 0 | J12: =MIN(B12,I12) -> 0 | K12: =B12-J12 -> 0 | L12: =I12-J12 -> 0 | M12: =J12*'Data Considered'!$B$11 -> 0 | N12: =Distributor!P12 -> 0 | O12: =H12*'Data Considered'!$B$12 -> 450 | P12: =N12-O12-S12-R12 -> -450 | Q12: =IF(A12=1,'Data Considered'!$B$18,Manufacturer!Q11+Manufacturer!P12) -> 43500 | R12: =J12*'Data Considered'!$D$11 -> 0 | S12: =L12*'Data Considered'!$B$22 -> 0 | T12: =K12*'Data Considered'!$B$26 -> 0 | U12: =ROUNDUP(L12/$B$108,0) -> 0 | V12: =U12+'Data Considered'!$B$15-0 -> 2 | W12: =O12+R12 -> 450 | X12: =IF(A12>2,OFFSET(M12,-2,0),0) -> 5000
A13: =A12+1 -> 12 | B13: =Distributor!H12 -> 0 | C13: =ROUNDUP(AVERAGE(B11,B12),0) -> 4 | D13: =3*C13 -> 12 | E13: =IF(A13>2,OFFSET(H13,-2,0),0) -> 126 | F13: =IF(A13=1,'Data Considered'!$B$5,L12+E13) -> 126 | G13: =F13+IF(A13>1,H12,0) -> 135 | H13: =IF(D13>G13,D13-G13,0) -> 0 | I13: =F13 -> 126 | J13: =MIN(B13,I13) -> 0 | K13: =B13-J13 -> 0 | L13: =I13-J13 -> 126 | M13: =J13*'Data Considered'!$B$11 -> 0 | N13: =Distributor!P13 -> 5000 | O13: =H13*'Data Considered'!$B$12 -> 0 | P13: =N13-O13-S13-R13 -> 4370 | Q13: =IF(A13=1,'Data Considered'!$B$18,Manufacturer!Q12+Manufacturer!P13) -> 47870 | R13: =J13*'Data Considered'!$D$11 -> 0 | S13: =L13*'Data Considered'!$B$22 -> 630 | T13: =K13*'Data Considered'!$B$26 -> 0 | U13: =ROUNDUP(L13/$B$108,0) -> 8 | V13: =U13+'Data Considered'!$B$15-0 -> 10 | W13: =O13+R13 -> 0 | X13: =IF(A13>2,OFFSET(M13,-2,0),0) -> 0
A14: =A13+1 -> 13 | B14: =Distributor!H13 -> 0 | C14: =ROUNDUP(AVERAGE(B12,B13),0) -> 0 | D14: =3*C14 -> 0 | E14: =IF(A14>2,OFFSET(H14,-2,0),0) -> 9 | F14: =IF(A14=1,'Data Considered'!$B$5,L13+E14) -> 135 | G14: =F14+IF(A14>1,H13,0) -> 135 | H14: =IF(D14>G14,D14-G14,0) -> 0 | I14: =F14 -> 135 | J14: =MIN(B14,I14) -> 0 | K14: =B14-J14 -> 0 | L14: =I14-J14 -> 135 | M14: =J14*'Data Considered'!$B$11 -> 0 | N14: =Distributor!P14 -> 0 | O14: =H14*'Data Considered'!$B$12 -> 0 | P14: =N14-O14-S14-R14 -> -675 | Q14: =IF(A14=1,'Data Considered'!$B$18,Manufacturer!Q13+Manufacturer!P14) -> 47195 | R14: =J14*'Data Considered'!$D$11 -> 0 | S14: =L14*'Data Considered'!$B$22 -> 675 | T14: =K14*'Data Considered'!$B$26 -> 0 | U14: =ROUNDUP(L14/$B$108,0) -> 9 | V14: =U14+'Data Considered'!$B$15-0 -> 11 | W14: =O14+R14 -> 0 | X14: =IF(A14>2,OFFSET(M14,-2,0),0) -> 0
A15: =A14+1 -> 14 | B15: =Distributor!H14 -> 87 | C15: =ROUNDUP(AVERAGE(B13,B14),0) -> 0 | D15: =3*C15 -> 0 | E15: =IF(A15>2,OFFSET(H15,-2,0),0) -> 0 | F15: =IF(A15=1,'Data Considered'!$B$5,L14+E15) -> 135 | G15: =F15+IF(A15>1,H14,0) -> 135 | H15: =IF(D15>G15,D15-G15,0) -> 0 | I15: =F15 -> 135 | J15: =MIN(B15,I15) -> 87 | K15: =B15-J15 -> 0 | L15: =I15-J15 -> 48 | M15: =J15*'Data Considered'!$B$11 -> 8700 | N15: =Distributor!P15 -> 0 | O15: =H15*'Data Considered'!$B$12 -> 0 | P15: =N15-O15-S15-R15 -> -675 | Q15: =IF(A15=1,'Data Considered'!$B$18,Manufacturer!Q14+Manufacturer!P15) -> 46520 | R15: =J15*'Data Considered'!$D$11 -> 435 | S15: =L15*'Data Considered'!$B$22 -> 240 | T15: =K15*'Data Considered'!$B$26 -> 0 | U15: =ROUNDUP(L15/$B$108,0) -> 3 | V15: =U15+'Data Considered'!$B$15-0 -> 5 | W15: =O15+R15 -> 435 | X15: =IF(A15>2,OFFSET(M15,-2,0),0) -> 0
... A105: =A104+1 -> 104 | B105: =Distributor!H104 -> 0 | C105: =ROUNDUP(AVERAGE(B103,B104),0) -> 17 | D105: =3*C105 -> 51 | E105: =IF(A105>2,OFFSET(H105,-2,0),0) -> 0 | F105: =IF(A105=1,'Data Considered'!$B$5,L104+E105) -> 41 | G105: =F105+IF(A105>1,H104,0) -> 123 | H105: =IF(D105>G105,D105-G105,0) -> 0 | I105: =F105 -> 41 | J105: =MIN(B105,I105) -> 0 | K105: =B105-J105 -> 0 | L105: =I105-J105 -> 41 | M105: =J105*'Data Considered'!$B$11 -> 0 | N105: =Distributor!P105 -> 4800 | O105: =H105*'Data Considered'!$B$12 -> 0 | P105: =N105-O105-S105-R105 -> 4595 | Q105: =IF(A105=1,'Data Considered'!$B$18,Manufacturer!Q104+Manufacturer!P105) -> 82465 | R105: =J105*'Data Considered'!$D$11 -> 0 | S105: =L105*'Data Considered'!$B$22 -> 205 | T105: =K105*'Data Considered'!$B$26 -> 0 | U105: =ROUNDUP(L105/$B$108,0) -> 3 | V105: =U105+'Data Considered'!$B$15-0 -> 5 | W105: =O105+R105 -> 0 | X105: =IF(A105>2,OFFSET(M105,-2,0),0) -> 3400
B107: AVERAGE DEMAND
B108: =AVERAGE(B2:B105) -> 16.298077
B110: VARIANCE DEMAND | H110: VARIANCE ORDER
B111: =_xlfn.VAR.S(B2:B105) -> 615.2598 | H111: =_xlfn.VAR.S(H2:H105) -> 1022.9028

Sheet Demand
A1: WEEK | B1: CUSTOMER DEMAND
A2: 1 | B2: 25
A3: =A2+1 -> 2 | B3: 24
A4: =A3+1 -> 3 | B4: 15
A5: =A4+1 -> 4 | B5: 21
A6: =A5+1 -> 5 | B6: 26
A7: =A6+1 -> 6 | B7: 24
A8: =A7+1 -> 7 | B8: 26
A9: =A8+1 -> 8 | B9: 9
A10: =A9+1 -> 9 | B10: 18
A11: =A10+1 -> 10 | B11: 22
A12: =A11+1 -> 11 | B12: 23
A13: =A12+1 -> 12 | B13: 24
A14: =A13+1 -> 13 | B14: 20
... A105: =A104+1 -> 104 | B105: 24

Sheet Performance
A1: METRIC | B1: MANUFACTURER | C1: DISTRIBUTOR | D1: RETAILER
A2: TOTAL DEMAND | B2: =SUM(INDEX(Manufacturer!B:B,'Data Considered'!B28+1):INDEX(Manufacturer!B:B,'Data Considered'!B29+1)) -> 990 | C2: =SUM(INDEX(Distributor!B:B, 'Data Considered'!B28+1) : INDEX(Distributor!B:B, 'Data Considered'!B29+1)) -> 1076 | D2: =SUM(INDEX(Retailer!B:B, 'Data Considered'!B28+1) : INDEX(Retailer!B:B, 'Data Considered'!B29+1)) -> 1176
A3: TOTAL UNITS SOLD | B3: =SUM(INDEX(Manufacturer!J:J,'Data Considered'!B28+1):INDEX(Manufacturer!J:J,'Data Considered'!B29+1)) -> 964 | C3: =SUM(INDEX(Distributor!J:J, 'Data Considered'!B28+1) : INDEX(Distributor!J:J, 'Data Considered'!B29+1)) -> 975 | D3: =SUM(INDEX(Retailer!J:J, 'Data Considered'!B28+1) : INDEX(Retailer!J:J, 'Data Considered'!B29+1)) -> 970
A4: LOST SALES | B4: =SUM(INDEX(Manufacturer!K:K,'Data Considered'!B28+1):INDEX(Manufacturer!K:K,'Data Considered'!B29+1)) -> 26 | C4: =SUM(INDEX(Distributor!K:K, 'Data Considered'!B28+1) : INDEX(Distributor!K:K, 'Data Considered'!B29+1)) -> 101 | D4: =SUM(INDEX(Retailer!K:K, 'Data Considered'!B28+1) : INDEX(Retailer!K:K, 'Data Considered'!B29+1)) -> 206
A5: FILL RATE | B5: =1-B4/B2 -> 0.97373737 | C5: =1-C4/C2 -> 0.90613383 | D5: =1-D4/D2 -> 0.82482993
A6: AVERAGE INVENTORY | B6: =AVERAGE(INDEX(Manufacturer!L:L, 'Data Considered'!B28+1) : INDEX(Manufacturer!L:L, 'Data Considered'!B29+1)) -> 73.516667 | C6: =AVERAGE(INDEX(Distributor!L:L, 'Data Considered'!B28+1) : INDEX(Distributor!L:L, 'Data Considered'!B29+1)) -> 25.133333 | D6: =AVERAGE(INDEX(Retailer!L:L, 'Data Considered'!B28+1) : INDEX(Retailer!L:L, 'Data Considered'!B29+1)) -> 8.2833333
A7: INVENTORY TURNOVER | B7: =B3/B6 -> 13.112673 | C7: =C3/C6 -> 38.793103 | D7: =D3/D6 -> 117.10262
A8: INVENTORY DURATION | B8: =ROUNDUP(B6/Manufacturer!B108,0) -> 5 | C8: =ROUNDUP(C6/Distributor!B108,0) -> 2 | D8: =ROUNDUP(D6/Retailer!B108,0) -> 1
A9: TOTAL HOLDING COST | B9: =SUM(INDEX(Manufacturer!S:S,'Data Considered'!B28+1):INDEX(Manufacturer!S:S,'Data Considered'!B29+1)) -> 22055 | C9: =SUM(INDEX(Distributor!T:T, 'Data Considered'!B28+1) : INDEX(Distributor!T:T, 'Data Considered'!B29+1)) -> 15080 | D9: =SUM(INDEX(Retailer!T:T, 'Data Considered'!B28+1) : INDEX(Retailer!T:T, 'Data Considered'!B29+1)) -> 7455
A10: TOTAL SHORTAGE COST | B10: =SUM(INDEX(Manufacturer!T:T, 'Data Considered'!B28+1) : INDEX(Manufacturer!T:T, 'Data Considered'!B29+1)) -> 1040 | C10: =SUM(INDEX(Distributor!U:U, 'Data Considered'!B28+1) : INDEX(Distributor!U:U, 'Data Considered'!B29+1)) -> 3030 | D10: =SUM(INDEX(Retailer!U:U, 'Data Considered'!B28+1) : INDEX(Retailer!U:U, 'Data Considered'!B29+1)) -> 8240
A11: TOTAL PURCHASE/PRODUCTION COST | B11: =SUM(INDEX(Manufacturer!O:O,'Data Considered'!B28+1):INDEX(Manufacturer!O:O,'Data Considered'!B29+1)) -> 47600 | C11: =SUM(INDEX(Distributor!O:O, 'Data Considered'!B28+1) : INDEX(Distributor!O:O, 'Data Considered'!B29+1)) -> 96400 | D11: =SUM(INDEX(Retailer!O:O, 'Data Considered'!B28+1) : INDEX(Retailer!O:O, 'Data Considered'!B29+1)) -> 135800
A12: TOTAL AMOUNT PAID TO UPSTREAM | C12: =SUM(INDEX(Distributor!P:P, 'Data Considered'!B28+1) : INDEX(Distributor!P:P, 'Data Considered'!B29+1)) -> 95400 | D12: =SUM(INDEX(Retailer!P:P, 'Data Considered'!B28+1) : INDEX(Retailer!P:P, 'Data Considered'!B29+1)) -> 136220
A13: TOTAL OVERHEAD EXPENSES | B13: =SUM(INDEX(Manufacturer!R:R,'Data Considered'!B28+1):INDEX(Manufacturer!R:R,'Data Considered'!B29+1)) -> 4820 | C13: =SUM(INDEX(Distributor!S:S, 'Data Considered'!B28+1) : INDEX(Distributor!S:S, 'Data Considered'!B29+1)) -> 6825 | D13: =SUM(INDEX(Retailer!S:S, 'Data Considered'!B28+1) : INDEX(Retailer!S:S, 'Data Considered'!B29+1)) -> 9700
A14: TOTAL OPERATIONAL COST | B14: =B9+B11+B13 -> 74475 | C14: =C9+C11+C13 -> 118305 | D14: =D9+D11+D13 -> 152955
A15: TOTAL REVENUE | B15: =SUM(INDEX(Manufacturer!X:X,'Data Considered'!B28+1):INDEX(Manufacturer!X:X,'Data Considered'!B29+1)) -> 89500 | C15: =SUM(INDEX(Distributor!Y:Y, 'Data Considered'!B28+1) : INDEX(Distributor!Y:Y, 'Data Considered'!B29+1)) -> 135240 | D15: =SUM(INDEX(Retailer!Y:Y, 'Data Considered'!B28+1) : INDEX(Retailer!Y:Y, 'Data Considered'!B29+1)) -> 174600
A16: TOTAL PROFIT | B16: =B15-B14 -> 15025 | C16: =C15-C9-C12-C13 -> 17935 | D16: =D15-D9-D12-D13 -> 21225
A17: NET CASH FLOW | B17: =SUM(INDEX(Manufacturer!P:P, 'Data Considered'!B28+1) : INDEX(Manufacturer!P:P, 'Data Considered'!B29+1)) -> 20925 | C17: =SUM(INDEX(Distributor!Q:Q, 'Data Considered'!B28+1) : INDEX(Distributor!Q:Q, 'Data Considered'!B29+1)) -> 18915 | D17: =SUM(INDEX(Retailer!Q:Q, 'Data Considered'!B28+1) : INDEX(Retailer!Q:Q, 'Data Considered'!B29+1)) -> 21225
A18: MINIMUM CASH POSITION | B18: =MIN(INDEX(Manufacturer!Q:Q, 'Data Considered'!B28+1) : INDEX(Manufacturer!Q:Q, 'Data Considered'!B29+1)) -> 44845 | C18: =MIN(INDEX(Distributor!R:R, 'Data Considered'!B28+1) : INDEX(Distributor!R:R, 'Data Considered'!B29+1)) -> 30645 | D18: =MIN(INDEX(Retailer!R:R, 'Data Considered'!B28+1) : INDEX(Retailer!R:R, 'Data Considered'!B29+1)) -> 27150
A19: NUMBER OF WEEKS WITH NEGATIVE NET CASH FLOW | B19: =COUNTIF(INDEX(Manufacturer!P:P, 'Data Considered'!B28+1) : INDEX(Manufacturer!P:P, 'Data Considered'!B29+1), "<0") -> 37 | C19: =COUNTIF(INDEX(Distributor!Q:Q, 'Data Considered'!B28+1) : INDEX(Distributor!Q:Q, 'Data Considered'!B29+1), "<0") -> 22 | D19: =COUNTIF(INDEX(Retailer!Q:Q, 'Data Considered'!B28+1) : INDEX(Retailer!Q:Q, 'Data Considered'!B29+1), "<0") -> 24
A20: ACCOUNTS RECEIVABLE DURATION | B20: 3 | C20: 3 | D20: 0
A21: ACCOUNTS PAYABLE DURATION | B21: 0 | C21: 2 | D21: 2
A22: CASH TO CASH CYCLE TIME | B22: =B8-B21+B20 -> 8 | C22: =C8-C21+C20 -> 3 | D22: =D8-D21+D20 -> -1
